streamad/__init__.py
streamad/base/__init__.py
streamad/base/detector.py
streamad/base/metrics.py
streamad/evaluate/__init__.py
streamad/evaluate/numenta_aware_metrics.py
streamad/evaluate/point_aware_metrics.py
streamad/evaluate/series_aware_metrics.py
streamad/evaluate/ts_metrics.py
streamad/meta.yaml
streamad/model/KNN_Detector.py
streamad/model/Mad_Dectector.py
streamad/model/OCSVM_Detector.py
streamad/model/SArima_Detector.py
streamad/model/SR_Detector.py
streamad/model/__init__.py
streamad/model/hstree_Detector.py
streamad/model/loda_Detector.py
streamad/model/random_Detector.py
streamad/model/rrcf_Detector.py
streamad/model/rshash_Detector.py
streamad/model/spot_Detector.py
streamad/model/xStream_Detector.py
streamad/model/zscore_Detector.py
streamad/model/zspot_Detector.py
streamad/process/__init__.py
streamad/process/tdigest_calibrator.py
streamad/process/vote_ensemble.py
streamad/process/weight_ensemble.py
streamad/process/zscore_calibrator.py
streamad/util/__init__.py
streamad/util/data/multiDS.csv
streamad/util/data/uniDS.csv
streamad/util/dataset.py
streamad/util/math_toolkit.py
streamad/util/plot.py
streamad/util/stream_generator.py
streamad/version.py
streamad-0.3.1.dist-info/LICENSE
streamad-0.3.1.dist-info/METADATA
streamad-0.3.1.dist-info/WHEEL
streamad-0.3.1.dist-info/RECORD
