Metadata-Version: 2.1
Name: streamad
Version: 0.3.1
Summary: An anomaly detection package for data streams.
License: Apache Software License
Author: Fengrui-Liu
Author-email: liufengrui18z@ict.ac.cn
Requires-Python: >=3.8,<4.0
Classifier: License :: Other/Proprietary License
Classifier: Programming Language :: Python :: 3
Classifier: Programming Language :: Python :: 3.8
Classifier: Programming Language :: Python :: 3.9
Classifier: Programming Language :: Python :: 3.10
Classifier: Programming Language :: Python :: 3.11
Requires-Dist: fast-histogram (>=0.11,<0.12)
Requires-Dist: mmh3 (>=3.0.0,<4.0.0)
Requires-Dist: numpy (>=1.22,<2.0)
Requires-Dist: pandas (>=1.3.0,<2.0.0)
Requires-Dist: plotly (>=5.14.1,<6.0.0)
Requires-Dist: pytest (>=7.3.1,<8.0.0)
Requires-Dist: pytest-cov (>=4.0.0,<5.0.0)
Requires-Dist: rrcf (>=0.4.4,<0.5.0)
Requires-Dist: scikit-learn (>=1.0.0,<2.0.0)
Requires-Dist: scipy (>=1.3.1,<2.0.0)
Requires-Dist: statsmodels (==0.13.5)
Requires-Dist: tdigest (>=0.5.2.2,<0.6.0.0)
